{"id":"fcb9cf6533bb4dfd802411d7fbfcc2a2","examples":[{"content":"Should ought","seen_by":[],"comments":[],"metadata":{"":86264," Round":"Jeopardy!"," Value":"$400","Answer":"ought","Air Date":2011,"Category":"RHYME-BOT","Question":"Should","Show Number":6240},"example_id":"5449854d-a931-4917-b55a-73dad492b807","annotations":[],"classifications":[]},{"content":"You often find this fruity adjective in front of the word \"keen\" when describing something swell peachy","seen_by":[],"comments":[],"metadata":{"":71072," Round":"Jeopardy!"," Value":"$200","Answer":"peachy","Air Date":2010,"Category":"FRUITY LANGUAGE","Question":"You often find this fruity adjective in front of the word \"keen\" when describing something swell","Show Number":6005},"example_id":"bbd4e3c8-77c8-4f6f-ac5e-5f18b6d85b3a","annotations":[],"classifications":[]},{"content":"Operation Baus Au, Tagalog for \"get it back\", was run by the U.S. military in this nation during World War II the Philippines","seen_by":[],"comments":[],"metadata":{"":152386," Round":"Double Jeopardy!"," Value":"$1600","Answer":"the Philippines","Air Date":2010,"Category":"ASIAN NATIONS","Question":"Operation Baus Au, Tagalog for \"get it back\", was run by the U.S. military in this nation during World War II","Show Number":5992},"example_id":"a00fe9ea-a907-4622-abb0-2ca3e0f39a2f","annotations":[],"classifications":[]},{"content":"Don't be \"mad\", it's where Mel Gibson took Max in the third installment \"Beyond Thunderdome\"","seen_by":[],"comments":[],"metadata":{"":142785," Round":"Double Jeopardy!"," Value":"$200","Answer":"\"Beyond Thunderdome\"","Air Date":1998,"Category":"THE GREAT \"BEYOND\"","Question":"Don't be \"mad\", it's where Mel Gibson took Max in the third installment","Show Number":3223},"example_id":"193de7f8-b1dd-4715-8e60-330ffcfc3f8c","annotations":[],"classifications":[]},{"content":"The heaviest Jupiter","seen_by":[],"comments":[],"metadata":{"":41222," Round":"Jeopardy!"," Value":"$200","Answer":"Jupiter","Air Date":2004,"Category":"PLANETARY DISTINCTIONS","Question":"The heaviest","Show Number":4617},"example_id":"14c7927a-cf54-40b7-9ab4-a6e3749904a8","annotations":[],"classifications":[]},{"content":"To make steak au poivre, cover your meat with this seasoning before broiling or sauteeing Pepper","seen_by":[],"comments":[],"metadata":{"":48907," Round":"Jeopardy!"," Value":"$300","Answer":"Pepper","Air Date":1997,"Category":"MEAT","Question":"To make steak au poivre, cover your meat with this seasoning before broiling or sauteeing","Show Number":2889},"example_id":"30dd178e-8b57-4379-930d-43986139f24f","annotations":[],"classifications":[]},{"content":"This former CBS anchorman is affectionately known as \"Uncle Walter\" Walter Cronkite","seen_by":[],"comments":[],"metadata":{"":69218," Round":"Jeopardy!"," Value":"$100","Answer":"Walter Cronkite","Air Date":1997,"Category":"PEOPLE","Question":"This former CBS anchorman is affectionately known as \"Uncle Walter\"","Show Number":3042},"example_id":"bd668e0d-571a-45e8-b191-c9d9490b1177","annotations":[],"classifications":[]},{"content":"From 1846 to 1849, he was surveyor of the port of Salem, Mass. Nathaniel Hawthorne","seen_by":[],"comments":[],"metadata":{"":187568," Round":"Double Jeopardy!"," Value":"$800","Answer":"Nathaniel Hawthorne","Air Date":1996,"Category":"AUTHORS","Question":"From 1846 to 1849, he was surveyor of the port of Salem, Mass.","Show Number":2624},"example_id":"2bfd42c2-0560-4f85-86ef-5580054212d1","annotations":[],"classifications":[]},{"content":"World Book says that only about 350 Gaulish words have become part of this modern language French","seen_by":[],"comments":[],"metadata":{"":191104," Round":"Jeopardy!"," Value":"$200","Answer":"French","Air Date":2000,"Category":"LANGUAGES","Question":"World Book says that only about 350 Gaulish words have become part of this modern language","Show Number":3666},"example_id":"78b7987d-2042-4312-b803-83284872f8ca","annotations":[],"classifications":[]},{"content":"Mont-Louis & Monte Perdido the Pyrenees","seen_by":[],"comments":[],"metadata":{"":11570," Round":"Jeopardy!"," Value":"$1000","Answer":"the Pyrenees","Air Date":2006,"Category":"TWIN PEAKS","Question":"Mont-Louis & Monte Perdido","Show Number":5081},"example_id":"a248ea04-6cc8-4704-8ba6-26d0d369ec28","annotations":[],"classifications":[]},{"content":"The mood of a verb: subj. subjunctive","seen_by":[],"comments":[],"metadata":{"":197903," Round":"Double Jeopardy!"," Value":"$2000","Answer":"subjunctive","Air Date":2010,"Category":"DICT. ABBREV.","Question":"The mood of a verb: subj.","Show Number":5884},"example_id":"7bd39df8-c99e-4f81-b5a5-b7dbc8fe2df5","annotations":[],"classifications":[]},{"content":"The university of this state at Machias is the easternmost 4-year college in the U.S. Maine","seen_by":[],"comments":[],"metadata":{"":174836," Round":"Jeopardy!"," Value":"$500","Answer":"Maine","Air Date":1997,"Category":"COLLEGES & UNIVERSITIES","Question":"The university of this state at Machias is the easternmost 4-year college in the U.S.","Show Number":2896},"example_id":"7ccacd64-87f2-45aa-ab21-14b43433da81","annotations":[],"classifications":[]},{"content":"The pledge written for this kids' sporting organization ends, \"Win or lose I will always do my best\" Little League Baseball","seen_by":[],"comments":[],"metadata":{"":99029," Round":"Jeopardy!"," Value":"$1,300","Answer":"Little League Baseball","Air Date":2011,"Category":"PLEDGES & OATHS","Question":"The pledge written for this kids' sporting organization ends, \"Win or lose I will always do my best\"","Show Number":6096},"example_id":"16e727b0-2f97-4d61-94da-6be2fd77b485","annotations":[],"classifications":[]},{"content":"Time is kept on Navy ships through the sounding of these; 8 of them signify the end of a 4-hour watch bells","seen_by":[],"comments":[],"metadata":{"":175908," Round":"Double Jeopardy!"," Value":"$400","Answer":"bells","Air Date":2005,"Category":"IN THE NAVY","Question":"Time is kept on Navy ships through the sounding of these; 8 of them signify the end of a 4-hour watch","Show Number":4765},"example_id":"d4c73a3f-43cf-45d0-939f-e064d20ccba6","annotations":[],"classifications":[]},{"content":"Plate pressure is compressing the Mediterranean, but this sea, bordering Greece, is expanding Aegean Sea","seen_by":[],"comments":[],"metadata":{"":81345," Round":"Jeopardy!"," Value":"$300","Answer":"Aegean Sea","Air Date":1989,"Category":"HODGEPODGE","Question":"Plate pressure is compressing the Mediterranean, but this sea, bordering Greece, is expanding","Show Number":1230},"example_id":"f5b8ce85-350d-4b20-bf72-8a1b00c0747c","annotations":[],"classifications":[]},{"content":"Tell, real or imagined, led the fight for Swiss freedom from this Austrian ruling house Habsburg","seen_by":[],"comments":[],"metadata":{"":31931," Round":"Double Jeopardy!"," Value":"$800","Answer":"Habsburg","Air Date":1992,"Category":"TELL","Question":"Tell, real or imagined, led the fight for Swiss freedom from this Austrian ruling house","Show Number":1856},"example_id":"feb2db53-2b6e-4fa2-b843-245dc2d8e39f","annotations":[],"classifications":[]},{"content":"Mel Brooks' \"High Anxiety\" poked fun at the films of this director who made his last film in 1976 Sir Alfred Hitchcock","seen_by":[],"comments":[],"metadata":{"":163802," Round":"Jeopardy!"," Value":"$300","Answer":"Sir Alfred Hitchcock","Air Date":1989,"Category":"FILMS OF THE '70S","Question":"Mel Brooks' \"High Anxiety\" poked fun at the films of this director who made his last film in 1976","Show Number":1147},"example_id":"c782a049-1ec2-4fc1-91f3-27d479f5345a","annotations":[],"classifications":[]},{"content":"In 1777 New Connecticut changed its name to this, the name the state's still known by Vermont","seen_by":[],"comments":[],"metadata":{"":27085," Round":"Double Jeopardy!"," Value":"$1,500","Answer":"Vermont","Air Date":1993,"Category":"U.S. STATES","Question":"In 1777 New Connecticut changed its name to this, the name the state's still known by","Show Number":2020},"example_id":"5417ab7f-2733-4176-afc0-27c5c8f76ae9","annotations":[],"classifications":[]},{"content":"(Hi, this is Dick Riordan, mayor of Los Angeles)  Renovated in 1993, this 88,000-seat facility first opened in May of 1923 Los Angeles Memorial Coliseum","seen_by":[],"comments":[],"metadata":{"":102028," Round":"Double Jeopardy!"," Value":"$1000","Answer":"Los Angeles Memorial Coliseum","Air Date":2000,"Category":"ARE YOU READY FOR SOME FOOTBALL?","Question":"(Hi, this is Dick Riordan, mayor of Los Angeles)  Renovated in 1993, this 88,000-seat facility first opened in May of 1923","Show Number":3742},"example_id":"3d793e24-e63f-4fed-ba9a-030077b9832e","annotations":[],"classifications":[]},{"content":"From the French for \"crust\", these cubes are delicious in salads croutons","seen_by":[],"comments":[],"metadata":{"":144815," Round":"Jeopardy!"," Value":"$200","Answer":"croutons","Air Date":2007,"Category":"SALAD","Question":"From the French for \"crust\", these cubes are delicious in salads","Show Number":5304},"example_id":"b06ccc2d-e44e-4bce-a639-c585114e69fe","annotations":[],"classifications":[]},{"content":"An acre of soil contains billions of nematodes, the round type of these seen here under the microscope worms","seen_by":[],"comments":[],"metadata":{"":113854," Round":"Double Jeopardy!"," Value":"$600","Answer":"worms","Air Date":2001,"Category":"SCIENCE","Question":"An acre of soil contains billions of nematodes, the round type of these seen here under the microscope","Show Number":3852},"example_id":"fe2e196a-8d47-4a1c-9686-5783652e6a63","annotations":[],"classifications":[]},{"content":"Troy, New York was home to the meatpacker who inspired this national symbol \"Uncle Sam\"","seen_by":[],"comments":[],"metadata":{"":22858," Round":"Jeopardy!"," Value":"$200","Answer":"\"Uncle Sam\"","Air Date":1997,"Category":"NEW YORK","Question":"Troy, New York was home to the meatpacker who inspired this national symbol","Show Number":2968},"example_id":"42ec2e1d-8389-43d9-9813-498f3c28b631","annotations":[],"classifications":[]},{"content":"In 1982 the Jarvik-7, the first permanent one of these, was implanted in patient Barney Clark an artificial heart","seen_by":[],"comments":[],"metadata":{"":149815," Round":"Jeopardy!"," Value":"$100","Answer":"an artificial heart","Air Date":1993,"Category":"SCIENCE & TECHNOLOGY","Question":"In 1982 the Jarvik-7, the first permanent one of these, was implanted in patient Barney Clark","Show Number":2048},"example_id":"ed449f6f-b34e-4533-ad2c-259950c348e9","annotations":[],"classifications":[]},{"content":"In 1983 this company introduced the Lisa, the first commercial computer to feature a mouse Apple","seen_by":[],"comments":[],"metadata":{"":74018," Round":"Double Jeopardy!"," Value":"$400","Answer":"Apple","Air Date":2010,"Category":"NON-EDIBLE FRUIT TERMS","Question":"In 1983 this company introduced the Lisa, the first commercial computer to feature a mouse","Show Number":5847},"example_id":"5583c3a8-92d5-4ade-8964-0db687bbae4c","annotations":[],"classifications":[]},{"content":"Phishing is not allowed when you use the newest version of this web browser from Mozilla Firefox","seen_by":[],"comments":[],"metadata":{"":209374," Round":"Jeopardy!"," Value":"$800","Answer":"Firefox","Air Date":2007,"Category":"TECH-KNOW","Question":"Phishing is not allowed when you use the newest version of this web browser from Mozilla","Show Number":5163},"example_id":"622bc770-e839-4f05-bbfc-9dc32911ec26","annotations":[],"classifications":[]},{"content":"A co-star of Kiefer Sutherland's in \"The Lost Boys\", we don't know why he felt the need for \"Speed 2\" Jason Patric","seen_by":[],"comments":[],"metadata":{"":216437," Round":"Double Jeopardy!"," Value":"$800","Answer":"Jason Patric","Air Date":2000,"Category":"HEY, GOOD LOOKIN'","Question":"A co-star of Kiefer Sutherland's in \"The Lost Boys\", we don't know why he felt the need for \"Speed 2\"","Show Number":3644},"example_id":"f521a52a-165e-4cfe-9491-64e8cccc24da","annotations":[],"classifications":[]},{"content":"As one of these rodeo personalities, Rob Smets has broken his neck twice; that's not funny Rodeo clown","seen_by":[],"comments":[],"metadata":{"":23516," Round":"Jeopardy!"," Value":"$200","Answer":"Rodeo clown","Air Date":1998,"Category":"THE RODEO","Question":"As one of these rodeo personalities, Rob Smets has broken his neck twice; that's not funny","Show Number":3083},"example_id":"a8ef917a-f625-42ea-9bd8-e3b301d422b1","annotations":[],"classifications":[]},{"content":"In baseball's American league, it's a player whose only job in the game is to bat for the pitcher as many times as needed the designated hitter","seen_by":[],"comments":[],"metadata":{"":173548," Round":"Jeopardy!"," Value":"$200","Answer":"the designated hitter","Air Date":2010,"Category":"SPORTS TALK","Question":"In baseball's American league, it's a player whose only job in the game is to bat for the pitcher as many times as needed","Show Number":5895},"example_id":"6ea81322-25b2-4229-9e99-37a062b326ec","annotations":[],"classifications":[]},{"content":"Beethoven said this great predecessor's name, which means \"brook\", should really be Meer, meaning \"sea\" Bach","seen_by":[],"comments":[],"metadata":{"":147431," Round":"Double Jeopardy!"," Value":"$1200","Answer":"Bach","Air Date":2007,"Category":"COMPOSERS","Question":"Beethoven said this great predecessor's name, which means \"brook\", should really be Meer, meaning \"sea\"","Show Number":5240},"example_id":"55d0b7fc-956c-47d4-aa34-c0ee8b3bf5e1","annotations":[],"classifications":[]},{"content":"(AUDIO DAILY DOUBLE): 20th century American poet heard here, reading one of his own works: \"With a Dutchman, I went once to Rembrandt Square, and down to Zanfra too.  I should have stayed & spent my lifetime on that beach.  I might have been a sailor, singing songs to myself only, or to a friend in Amsterdam...\" Rod McKuen","seen_by":[],"comments":[],"metadata":{"":57571," Round":"Double Jeopardy!"," Value":"$1,000","Answer":"Rod McKuen","Air Date":1990,"Category":"POETS","Question":"(AUDIO DAILY DOUBLE): 20th century American poet heard here, reading one of his own works: \"With a Dutchman, I went once to Rembrandt Square, and down to Zanfra too.  I should have stayed & spent my lifetime on that beach.  I might have been a sailor, singing songs to myself only, or to a friend in Amsterdam...\"","Show Number":1267},"example_id":"7a6bade1-5a2e-4a13-aee8-7ffb5cba5f5e","annotations":[],"classifications":[]},{"content":"The drill instructor in \"An Officer and a Gentleman\", he turned down an offer to play pro basketball Louis Gossett, Jr.","seen_by":[],"comments":[],"metadata":{"":158887," Round":"Jeopardy!"," Value":"$500","Answer":"Louis Gossett, Jr.","Air Date":1997,"Category":"FILM STARS","Question":"The drill instructor in \"An Officer and a Gentleman\", he turned down an offer to play pro basketball","Show Number":2966},"example_id":"c3a86fc8-e547-4244-93e1-c855fcde9da7","annotations":[],"classifications":[]},{"content":"P.T. Barnum didn't have this actress' leg to stand on when she refused his $10,000 offer for it Sarah Bernhardt","seen_by":[],"comments":[],"metadata":{"":15241," Round":"Jeopardy!"," Value":"$1000","Answer":"Sarah Bernhardt","Air Date":2008,"Category":"MISSING BODY PARTS","Question":"P.T. Barnum didn't have this actress' leg to stand on when she refused his $10,000 offer for it","Show Number":5408},"example_id":"befc3ed7-05d7-4e04-9444-c9c0d9d88b0c","annotations":[],"classifications":[]},{"content":"The only British monarch of the 20th century not to produce an heir Edward VIII","seen_by":[],"comments":[],"metadata":{"":210010," Round":"Final Jeopardy!"," Value":null,"Answer":"Edward VIII","Air Date":2004,"Category":"BRITISH ROYALTY","Question":"The only British monarch of the 20th century not to produce an heir","Show Number":4520},"example_id":"44de7a92-5c99-4241-9de4-7c8e83e5cb5d","annotations":[],"classifications":[]},{"content":"A single wicker container should not hold the entire output of thy hen don't put all your eggs in one basket","seen_by":[],"comments":[],"metadata":{"":191412," Round":"Jeopardy!"," Value":"$300","Answer":"don't put all your eggs in one basket","Air Date":1985,"Category":"IN OTHER WORDS...","Question":"A single wicker container should not hold the entire output of thy hen","Show Number":310},"example_id":"9d4e5bf6-6455-4ff2-a1b0-3b998f0970e8","annotations":[],"classifications":[]},{"content":"Richard Middlemas gets crushed by an elephant in \"The Surgeon's Daughter\", an 1827 tale by this Edinburgher Sir Walter Scott","seen_by":[],"comments":[],"metadata":{"":134302," Round":"Jeopardy!"," Value":"$800","Answer":"Sir Walter Scott","Air Date":2008,"Category":"LITERATURE","Question":"Richard Middlemas gets crushed by an elephant in \"The Surgeon's Daughter\", an 1827 tale by this Edinburgher","Show Number":5458},"example_id":"b3ac0770-ac71-41c6-881e-97b2bfc0b146","annotations":[],"classifications":[]},{"content":"The Pentagon later admitted this system named for a film worked because a guide beacon was put on the target Star Wars","seen_by":[],"comments":[],"metadata":{"":207606," Round":"Jeopardy!"," Value":"$1000","Answer":"Star Wars","Air Date":2007,"Category":"SPIN-AGE","Question":"The Pentagon later admitted this system named for a film worked because a guide beacon was put on the target","Show Number":5297},"example_id":"5e72cd2b-584b-486d-ad18-70c14efe2a4f","annotations":[],"classifications":[]},{"content":"An athlete with this inflammation that affects a certain arm joint may make quite a \"racket\" Tennis elbow/tendonitis","seen_by":[],"comments":[],"metadata":{"":74598," Round":"Double Jeopardy!"," Value":"$400","Answer":"Tennis elbow/tendonitis","Air Date":1998,"Category":"TAKE \"TEN\"","Question":"An athlete with this inflammation that affects a certain arm joint may make quite a \"racket\"","Show Number":3153},"example_id":"735505e7-c550-4d7e-bd52-f697a5ccc23d","annotations":[],"classifications":[]},{"content":"It's found on the head of a monarch and on the end of a watch stem crown","seen_by":[],"comments":[],"metadata":{"":44598," Round":"Double Jeopardy!"," Value":"$400","Answer":"crown","Air Date":1996,"Category":"PARTS","Question":"It's found on the head of a monarch and on the end of a watch stem","Show Number":2821},"example_id":"577d7080-4dea-498e-a0b3-32ede6c9f08f","annotations":[],"classifications":[]},{"content":"This amendment guarantees that a citizen shall not \"be compelled in any criminal case to be a witness against himself\" the 5th Amendment","seen_by":[],"comments":[],"metadata":{"":160350," Round":"Jeopardy!"," Value":"$200","Answer":"the 5th Amendment","Air Date":2005,"Category":"THE BILL OF RIGHTS","Question":"This amendment guarantees that a citizen shall not \"be compelled in any criminal case to be a witness against himself\"","Show Number":4884},"example_id":"20f92b40-be91-4a4a-88e6-ddf6d4dfbdd7","annotations":[],"classifications":[]},{"content":"Not far from Roanoke, this military school broke a 158 year tradition & admitted women in 1997 VMI (Virginia Military Institute)","seen_by":[],"comments":[],"metadata":{"":153786," Round":"Jeopardy!"," Value":"$200","Answer":"VMI (Virginia Military Institute)","Air Date":1998,"Category":"SEX CHANGES","Question":"Not far from Roanoke, this military school broke a 158 year tradition & admitted women in 1997","Show Number":3098},"example_id":"cdcc43c1-a3e8-48cc-b498-d2ea10c7f862","annotations":[],"classifications":[]},{"content":"The Big 12: a dozen athletic powerhouses, 4 of them in this state Texas","seen_by":[],"comments":[],"metadata":{"":83773," Round":"Double Jeopardy!"," Value":"$1200","Answer":"Texas","Air Date":2009,"Category":"THEY'RE BIG","Question":"The Big 12: a dozen athletic powerhouses, 4 of them in this state","Show Number":5800},"example_id":"b8c7f971-f9f6-46d0-ad56-360431f15d87","annotations":[],"classifications":[]},{"content":"1797-1801 Abigail Adams","seen_by":[],"comments":[],"metadata":{"":62786," Round":"Jeopardy!"," Value":"$600","Answer":"Abigail Adams","Air Date":2005,"Category":"FIRST LADIES' TERMS OF SERVICE","Question":"1797-1801","Show Number":4747},"example_id":"a7a953e2-efff-46d4-b88c-e937277d68c7","annotations":[],"classifications":[]},{"content":"The last name of author Stephenie or the first name of gangster Lansky Meyer","seen_by":[],"comments":[],"metadata":{"":49670," Round":"Double Jeopardy!"," Value":"$2000","Answer":"Meyer","Air Date":2010,"Category":"THE \"EYE\"s HAVE IT","Question":"The last name of author Stephenie or the first name of gangster Lansky","Show Number":5980},"example_id":"7a9c217d-117b-4bf0-a5ac-d02ea797a1b7","annotations":[],"classifications":[]},{"content":"\"Tusk\", \"Tango in the Night\", \"The Dance\" Fleetwood Mac","seen_by":[],"comments":[],"metadata":{"":133304," Round":"Double Jeopardy!"," Value":"$400","Answer":"Fleetwood Mac","Air Date":1999,"Category":"DISCOGRAPHIES","Question":"\"Tusk\", \"Tango in the Night\", \"The Dance\"","Show Number":3524},"example_id":"dac1c153-ca1e-4520-9bed-a1783b51b28f","annotations":[],"classifications":[]},{"content":"Many politicos were saying they didn't know Jack when this lobbyist pled guilty to 3 felonies in January 2006 Jack Abramoff","seen_by":[],"comments":[],"metadata":{"":195770," Round":"Jeopardy!"," Value":"$400","Answer":"Jack Abramoff","Air Date":2006,"Category":"PAC-MAN","Question":"Many politicos were saying they didn't know Jack when this lobbyist pled guilty to 3 felonies in January 2006","Show Number":5024},"example_id":"2007cc69-9142-481e-8927-731416192855","annotations":[],"classifications":[]},{"content":"I'm now using the Firefox web browser that got its start from this Time Warner company's Netscape division AOL","seen_by":[],"comments":[],"metadata":{"":171178," Round":"Jeopardy!"," Value":"$600","Answer":"AOL","Air Date":2005,"Category":"MY PC LIFE","Question":"I'm now using the Firefox web browser that got its start from this Time Warner company's Netscape division","Show Number":4778},"example_id":"b30f79a2-6a1e-47ee-abfd-789fcd9209d5","annotations":[],"classifications":[]},{"content":"It's a bovine term for a sharp bend in a river ox-bow","seen_by":[],"comments":[],"metadata":{"":143860," Round":"Double Jeopardy!"," Value":"$1600","Answer":"ox-bow","Air Date":2004,"Category":"IT'S A ZOO IN HERE!","Question":"It's a bovine term for a sharp bend in a river","Show Number":4490},"example_id":"130b68f6-f86a-4a7c-b850-0b8ce4a2398b","annotations":[],"classifications":[]},{"content":"Ending the third of the wars named for them, Billy Bowlegs of this tribe surrendered with his warriors in 1858 the Seminole tribe","seen_by":[],"comments":[],"metadata":{"":33698," Round":"Double Jeopardy!"," Value":"$2000","Answer":"the Seminole tribe","Air Date":2011,"Category":"THE SUNSHINE STATE","Question":"Ending the third of the wars named for them, Billy Bowlegs of this tribe surrendered with his warriors in 1858","Show Number":6112},"example_id":"67a0a348-57bd-4b52-b71e-63e9015bda01","annotations":[],"classifications":[]},{"content":"Named for its surveyors, this \"line\" was once considered the boundary between slave & free states Mason-Dixon Line","seen_by":[],"comments":[],"metadata":{"":124779," Round":"Jeopardy!"," Value":"$200","Answer":"Mason-Dixon Line","Air Date":1997,"Category":"\"M.D.\"s","Question":"Named for its surveyors, this \"line\" was once considered the boundary between slave & free states","Show Number":2926},"example_id":"d0130904-0bf7-4ea8-98ce-b30aacc537d1","annotations":[],"classifications":[]},{"content":"Goalie, throw-in, midfielder soccer","seen_by":[],"comments":[],"metadata":{"":18149," Round":"Jeopardy!"," Value":"$400","Answer":"soccer","Air Date":2007,"Category":"SPORTS TERMS","Question":"Goalie, throw-in, midfielder","Show Number":5280},"example_id":"22003b83-ad20-4fe5-8e5d-122c89290fa6","annotations":[],"classifications":[]},{"content":"Of the first 2 people to make offerings to God, the one who had his rejected Cain","seen_by":[],"comments":[],"metadata":{"":168523," Round":"Jeopardy!"," Value":"$100","Answer":"Cain","Air Date":1999,"Category":"THE OLD TESTAMENT","Question":"Of the first 2 people to make offerings to God, the one who had his rejected","Show Number":3522},"example_id":"f6bfdd09-e7b1-4af4-b46f-9952eeaeac62","annotations":[],"classifications":[]},{"content":"This anime show didn't start on TV; its characters were first part of Nintendo's \"Pocket Monsters\" Pokémon","seen_by":[],"comments":[],"metadata":{"":157280," Round":"Double Jeopardy!"," Value":"$400","Answer":"Pokémon","Air Date":2008,"Category":"WE HAVE MET THE ANIME","Question":"This anime show didn't start on TV; its characters were first part of Nintendo's \"Pocket Monsters\"","Show Number":5488},"example_id":"06eaa207-11e3-4c9e-911f-5031385aee76","annotations":[],"classifications":[]},{"content":"He named the ocean \"Pacific\" after many turbulent detours in South America while searching for Asia (Ferdinand) Magellan","seen_by":[],"comments":[],"metadata":{"":46640," Round":"Jeopardy!"," Value":"$800","Answer":"(Ferdinand) Magellan","Air Date":2006,"Category":"OFF COURSE, OFF COURSE","Question":"He named the ocean \"Pacific\" after many turbulent detours in South America while searching for Asia","Show Number":5058},"example_id":"4fd0b39f-4c94-42b1-b356-29036adfcd96","annotations":[],"classifications":[]},{"content":"This man for whom a large city is named became governor of Tennessee in 1827 & governor of Texas in 1859 Sam Houston","seen_by":[],"comments":[],"metadata":{"":103947," Round":"Jeopardy!"," Value":"$200","Answer":"Sam Houston","Air Date":2004,"Category":"FAMOUS AMERICANS","Question":"This man for whom a large city is named became governor of Tennessee in 1827 & governor of Texas in 1859","Show Number":4508},"example_id":"ac7355fe-e509-4552-9431-63799271007c","annotations":[],"classifications":[]},{"content":"Founded by Spanish immigrants in 1936, the nation's largest Hispanic food company has this artistic name Goya","seen_by":[],"comments":[],"metadata":{"":55565," Round":"Jeopardy!"," Value":"$1000","Answer":"Goya","Air Date":2006,"Category":"ON THE \"GO\"","Question":"Founded by Spanish immigrants in 1936, the nation's largest Hispanic food company has this artistic name","Show Number":4920},"example_id":"66c185fb-c20e-45de-945d-8a8d1096a67a","annotations":[],"classifications":[]},{"content":"Her dad was Ptolemy XII; lucky no. XIII, 10 years old at the time, became her co-ruler & husband Cleopatra","seen_by":[],"comments":[],"metadata":{"":121798," Round":"Jeopardy!"," Value":"$400","Answer":"Cleopatra","Air Date":2007,"Category":"PTOLEMY...WHY NOT TAKE PTOLEMY?","Question":"Her dad was Ptolemy XII; lucky no. XIII, 10 years old at the time, became her co-ruler & husband","Show Number":5258},"example_id":"b1219929-4ba9-4f6f-8a17-780e833f5472","annotations":[],"classifications":[]},{"content":"Known for its stampede, this largest Alberta city is called Canada's oil & gas capital Calgary","seen_by":[],"comments":[],"metadata":{"":52502," Round":"Double Jeopardy!"," Value":"$200","Answer":"Calgary","Air Date":1997,"Category":"CANADIAN CITIES","Question":"Known for its stampede, this largest Alberta city is called Canada's oil & gas capital","Show Number":2912},"example_id":"22d064a0-105b-4f11-a52a-acd15fc65df4","annotations":[],"classifications":[]},{"content":"\"Pore Jud is Daid\" is a song in this exclamatory 1943 Rodgers & Hammerstein musical \"Oklahoma!\"","seen_by":[],"comments":[],"metadata":{"":104890," Round":"Double Jeopardy!"," Value":"$1,200","Answer":"\"Oklahoma!\"","Air Date":1998,"Category":"EXCLAMATION POINTS","Question":"\"Pore Jud is Daid\" is a song in this exclamatory 1943 Rodgers & Hammerstein musical","Show Number":3207},"example_id":"13d861a0-76d0-4c80-9429-fb7f7533602f","annotations":[],"classifications":[]},{"content":"A year after Kelly Ripa married him at the Chapel of the Bells, their characters tied the knot on \"All My Children\" Mark Consuelos","seen_by":[],"comments":[],"metadata":{"":30452," Round":"Jeopardy!"," Value":"$800","Answer":"Mark Consuelos","Air Date":2006,"Category":"LET'S GET MARRIED IN VEGAS!","Question":"A year after Kelly Ripa married him at the Chapel of the Bells, their characters tied the knot on \"All My Children\"","Show Number":4979},"example_id":"3f445520-750d-40d7-84e7-a91b97ef1417","annotations":[],"classifications":[]},{"content":"In 1941 80,000 Ford workers voted to be represented by this union rather than the AFL CIO (Congress of Industrial Organizations)","seen_by":[],"comments":[],"metadata":{"":190723," Round":"Double Jeopardy!"," Value":"$1200","Answer":"CIO (Congress of Industrial Organizations)","Air Date":2003,"Category":"ORGANIZATIONS","Question":"In 1941 80,000 Ford workers voted to be represented by this union rather than the AFL","Show Number":4325},"example_id":"dbeb4acf-9fd4-4da8-805f-a8fbcd4edccc","annotations":[],"classifications":[]},{"content":"After 1953 & for the next 28 years, this car seen here was built only in St. Louis: Chevrolet Corvette","seen_by":[],"comments":[],"metadata":{"":96711," Round":"Double Jeopardy!"," Value":"$600","Answer":"Chevrolet Corvette","Air Date":1998,"Category":"IN ST. LOUIS","Question":"After 1953 & for the next 28 years, this car seen here was built only in St. Louis:","Show Number":3146},"example_id":"dce1e0d0-21bb-4846-92eb-db9094ee9f13","annotations":[],"classifications":[]},{"content":"In 1913 this alloy was invented by Harry Brearley of Sheffield, England, a city known for its cutlery since before 1400 stainless steel","seen_by":[],"comments":[],"metadata":{"":81039," Round":"Final Jeopardy!"," Value":null,"Answer":"stainless steel","Air Date":2005,"Category":"TECHNOLOGY","Question":"In 1913 this alloy was invented by Harry Brearley of Sheffield, England, a city known for its cutlery since before 1400","Show Number":4682},"example_id":"770c2303-207e-423f-b4e4-ab519d36273e","annotations":[],"classifications":[]},{"content":"Jedi Qui-Gon Jinn fights a deadly lightsaber duel with this evil Sith apprentice Darth Maul","seen_by":[],"comments":[],"metadata":{"":124232," Round":"Double Jeopardy!"," Value":"$1000","Answer":"Darth Maul","Air Date":1999,"Category":"THE PHANTOM MENACE","Question":"Jedi Qui-Gon Jinn fights a deadly lightsaber duel with this evil Sith apprentice","Show Number":3493},"example_id":"3835c7c6-2fcf-487c-8c40-458f9f0ff958","annotations":[],"classifications":[]},{"content":"An old proverb tells us \"there is truth in\" this beverage wine","seen_by":[],"comments":[],"metadata":{"":182774," Round":"Double Jeopardy!"," Value":"$400","Answer":"wine","Air Date":2004,"Category":"4-LETTER \"W\"ORDS","Question":"An old proverb tells us \"there is truth in\" this beverage","Show Number":4660},"example_id":"a9e06568-f417-4df7-b6fd-c2f0e2a0f332","annotations":[],"classifications":[]},{"content":"\"The Lonely Silver Rain\" was the 21st & last of this mystery author's novels featuring Travis McGee John D. MacDonald","seen_by":[],"comments":[],"metadata":{"":190969," Round":"Double Jeopardy!"," Value":"$1600","Answer":"John D. MacDonald","Air Date":2011,"Category":"THE 21st","Question":"\"The Lonely Silver Rain\" was the 21st & last of this mystery author's novels featuring Travis McGee","Show Number":6273},"example_id":"ac90c34d-bb09-4705-b23b-fe934b16f7f8","annotations":[],"classifications":[]},{"content":"He's the giraffe mascot for Toys 'R Us Geoffrey","seen_by":[],"comments":[],"metadata":{"":200669," Round":"Jeopardy!"," Value":"$200","Answer":"Geoffrey","Air Date":2005,"Category":"ADVERTISING MASCOTS","Question":"He's the giraffe mascot for Toys 'R Us","Show Number":4687},"example_id":"06068441-c007-495d-89bf-626db7f732ca","annotations":[],"classifications":[]},{"content":"Lyrics to some of the musical numbers in this Johnny Depp film were written by Roald Dahl Charlie and the Chocolate Factory","seen_by":[],"comments":[],"metadata":{"":138243," Round":"Jeopardy!"," Value":"$1000","Answer":"Charlie and the Chocolate Factory","Air Date":2008,"Category":"DEPP PERCEPTION","Question":"Lyrics to some of the musical numbers in this Johnny Depp film were written by Roald Dahl","Show Number":5480},"example_id":"d3475b68-8438-42e1-b524-41de7f645fa0","annotations":[],"classifications":[]},{"content":"Bootsy Collins","seen_by":[],"comments":[],"metadata":{"":160013," Round":"Jeopardy!"," Value":"$1000","Answer":"Collins","Air Date":2005,"Category":"TOP 40 LAST NAMES","Question":"Bootsy","Show Number":4804},"example_id":"9a2fa127-2159-41c0-a905-4c8d9010cbb3","annotations":[],"classifications":[]},{"content":"A shooting in Morocco touches off a story spanning 3 continents in this 2006 Gonzalez Inarritu film Babel","seen_by":[],"comments":[],"metadata":{"":11043," Round":"Double Jeopardy!"," Value":"$3,500","Answer":"Babel","Air Date":2007,"Category":"MEXICAN MOVIE MAKERS","Question":"A shooting in Morocco touches off a story spanning 3 continents in this 2006 Gonzalez Inarritu film","Show Number":5311},"example_id":"f0b9ba55-553d-4773-9275-1c6539b9b59f","annotations":[],"classifications":[]},{"content":"Gabourey Sidibe, Mo'nique Precious","seen_by":[],"comments":[],"metadata":{"":54126," Round":"Double Jeopardy!"," Value":"$400","Answer":"Precious","Air Date":2010,"Category":"MOVIE BY CAST","Question":"Gabourey Sidibe, Mo'nique","Show Number":5943},"example_id":"937d5bb1-8d8a-4b72-9513-6705bfd0e59e","annotations":[],"classifications":[]},{"content":"The angel Moroni told him about the golden plates from which the Book of Mormon was translated Joseph Smith","seen_by":[],"comments":[],"metadata":{"":144576," Round":"Jeopardy!"," Value":"$100","Answer":"Joseph Smith","Air Date":1990,"Category":"RELIGION","Question":"The angel Moroni told him about the golden plates from which the Book of Mormon was translated","Show Number":1324},"example_id":"a1f7eeb8-1f1d-4635-b884-46a2d55e6604","annotations":[],"classifications":[]},{"content":"The half-mile route for this annual event begins at Santo Domingo Street in Pamplona the Running of the Bulls","seen_by":[],"comments":[],"metadata":{"":188718," Round":"Jeopardy!"," Value":"$600","Answer":"the Running of the Bulls","Air Date":2007,"Category":"HOLIDAYS & OBSERVANCES","Question":"The half-mile route for this annual event begins at Santo Domingo Street in Pamplona","Show Number":5220},"example_id":"eda5e776-30a2-4de6-8994-cfdc520ee76c","annotations":[],"classifications":[]},{"content":"Hr. corresponds to this German title of respect Herr","seen_by":[],"comments":[],"metadata":{"":207698," Round":"Jeopardy!"," Value":"$400","Answer":"Herr","Air Date":2010,"Category":"HR","Question":"Hr. corresponds to this German title of respect","Show Number":5838},"example_id":"dcb5b607-1971-4873-a406-c5c6702195f0","annotations":[],"classifications":[]},{"content":"One successful roll for Pete Weber or pitch for Eric Gagne a strike","seen_by":[],"comments":[],"metadata":{"":21865," Round":"Double Jeopardy!"," Value":"$400","Answer":"a strike","Air Date":2006,"Category":"2-SPORT TERMS","Question":"One successful roll for Pete Weber or pitch for Eric Gagne","Show Number":4929},"example_id":"0ba768b6-5a80-4a7f-a302-81384c995332","annotations":[],"classifications":[]},{"content":"The name of this hospital volunteer comes from the red- & white-striped uniform a Candy Striper","seen_by":[],"comments":[],"metadata":{"":128510," Round":"Double Jeopardy!"," Value":"$1600","Answer":"a Candy Striper","Air Date":2006,"Category":"GET INVOLVED","Question":"The name of this hospital volunteer comes from the red- & white-striped uniform","Show Number":4933},"example_id":"f6bfe9d6-0ef6-4ea1-9ea5-35ffe8489a3d","annotations":[],"classifications":[]},{"content":"Seen here, he learned to golf lefty by standing opposite his father & imitating Dad's swing Phil Mickelson","seen_by":[],"comments":[],"metadata":{"":101377," Round":"Double Jeopardy!"," Value":"$1600","Answer":"Phil Mickelson","Air Date":2003,"Category":"SPORTS LEFTIES","Question":"Seen here, he learned to golf lefty by standing opposite his father & imitating Dad's swing","Show Number":4262},"example_id":"2c6ac029-008c-4da1-aa14-654344913827","annotations":[],"classifications":[]},{"content":"Of \"the Four Corners states\", this is the southwestern one Arizona","seen_by":[],"comments":[],"metadata":{"":124994," Round":"Jeopardy!"," Value":"$200","Answer":"Arizona","Air Date":2007,"Category":"STATE BORDERS","Question":"Of \"the Four Corners states\", this is the southwestern one","Show Number":5300},"example_id":"0ac7da1a-5856-4932-9644-e6f11564d45c","annotations":[],"classifications":[]},{"content":"This film's title is the second half of an old boxing expression The Harder They Fall","seen_by":[],"comments":[],"metadata":{"":91394," Round":"Double Jeopardy!"," Value":"$800","Answer":"The Harder They Fall","Air Date":1999,"Category":"JOCKS ON FILM","Question":"This film's title is the second half of an old boxing expression","Show Number":3356},"example_id":"de67ba55-cc35-4098-b76d-016a2c0c29c5","annotations":[],"classifications":[]},{"content":"McGill University, University of Regina Canada","seen_by":[],"comments":[],"metadata":{"":89627," Round":"Double Jeopardy!"," Value":"$400","Answer":"Canada","Air Date":2007,"Category":"COUNTRIES BY COLLEGE","Question":"McGill University, University of Regina","Show Number":5229},"example_id":"93fa0777-f601-4470-97e9-e5d526921002","annotations":[],"classifications":[]},{"content":"Related to the word \"increase\", it's a small change in a variable representing distance or time increment","seen_by":[],"comments":[],"metadata":{"":122509," Round":"Double Jeopardy!"," Value":"$2000","Answer":"increment","Air Date":2004,"Category":"CALCULUS","Question":"Related to the word \"increase\", it's a small change in a variable representing distance or time","Show Number":4615},"example_id":"073982e6-d1cd-460c-af5b-15427d1f58e5","annotations":[],"classifications":[]},{"content":"This \"dogged\" Sherlock Holmes novel was published in 1902 The Hound of the Baskervilles","seen_by":[],"comments":[],"metadata":{"":72402," Round":"Double Jeopardy!"," Value":"$400","Answer":"The Hound of the Baskervilles","Air Date":2007,"Category":"YO, HOLMES!","Question":"This \"dogged\" Sherlock Holmes novel was published in 1902","Show Number":5295},"example_id":"3fed16ea-913f-4d1c-810b-14293f12aee8","annotations":[],"classifications":[]},{"content":"After the death of Maria Theresa in 1683, this \"Sun King\" secretly married Madame de Maintenon Louis XIV","seen_by":[],"comments":[],"metadata":{"":56606," Round":"Double Jeopardy!"," Value":"$800","Answer":"Louis XIV","Air Date":2000,"Category":"FRENCH HISTORY","Question":"After the death of Maria Theresa in 1683, this \"Sun King\" secretly married Madame de Maintenon","Show Number":3533},"example_id":"fce02da6-20e6-4c29-9d9e-0503d00a1cde","annotations":[],"classifications":[]},{"content":"On this HBO show Gabriel Byrne plays a therapist with as many issues as his patients In Treatment","seen_by":[],"comments":[],"metadata":{"":131889," Round":"Double Jeopardy!"," Value":"$1600","Answer":"In Treatment","Air Date":2009,"Category":"\"TRICK\" OR \"TREAT\"","Question":"On this HBO show Gabriel Byrne plays a therapist with as many issues as his patients","Show Number":5780},"example_id":"294a81f8-3b61-4e23-8b0d-5b74003562c5","annotations":[],"classifications":[]},{"content":"He had the right stuff to be the first Ohioan elected to the U.S. senate for 4 consecutive terms John Glenn","seen_by":[],"comments":[],"metadata":{"":166947," Round":"Jeopardy!"," Value":"$600","Answer":"John Glenn","Air Date":2011,"Category":"RONS, DONS & JOHNS","Question":"He had the right stuff to be the first Ohioan elected to the U.S. senate for 4 consecutive terms","Show Number":6205},"example_id":"42acf100-18ce-47c2-979b-4b36c9f7412a","annotations":[],"classifications":[]},{"content":"Almost everything most insects do is related to these 2 survival activities eating & mating","seen_by":[],"comments":[],"metadata":{"":158572," Round":"Jeopardy!"," Value":"$300","Answer":"eating & mating","Air Date":1986,"Category":"INSECTS","Question":"Almost everything most insects do is related to these 2 survival activities","Show Number":367},"example_id":"1bffe353-c8a4-4c15-972c-0dbe628f798e","annotations":[],"classifications":[]},{"content":"Usual profession of John Grisham's heroes, including \"The Street\" one Lawyers","seen_by":[],"comments":[],"metadata":{"":200213," Round":"Double Jeopardy!"," Value":"$200","Answer":"Lawyers","Air Date":2001,"Category":"BESTSELLERS","Question":"Usual profession of John Grisham's heroes, including \"The Street\" one","Show Number":3766},"example_id":"cffad8f0-90bc-4e32-a62b-0da2e3eff096","annotations":[],"classifications":[]},{"content":"(Sarah of the Clue Crew ready to fall backwards into a swimming pool)  I'm about to take this drink company's famous plunge from TV ads Nestea iced tea","seen_by":[],"comments":[],"metadata":{"":48303," Round":"Jeopardy!"," Value":"$200","Answer":"Nestea iced tea","Air Date":2001,"Category":"FOOD & DRINK","Question":"(Sarah of the Clue Crew ready to fall backwards into a swimming pool)  I'm about to take this drink company's famous plunge from TV ads","Show Number":3943},"example_id":"065c2d64-aa36-45b0-8050-5719f078f8f3","annotations":[],"classifications":[]},{"content":"Ranchers formed the territory of Cimarron in 1887; it lasted until 1890 when it became this state's western panhandle Oklahoma","seen_by":[],"comments":[],"metadata":{"":157047," Round":"Double Jeopardy!"," Value":"$1200","Answer":"Oklahoma","Air Date":2008,"Category":"U.S. GEOGRAPHY","Question":"Ranchers formed the territory of Cimarron in 1887; it lasted until 1890 when it became this state's western panhandle","Show Number":5372},"example_id":"4cc9e4a9-ca38-4dd4-9343-b38c322b6d58","annotations":[],"classifications":[]},{"content":"At the time this prime minister separated from his wife in '77, she denied rumors linking her with Mick Jagger Pierre Trudeau","seen_by":[],"comments":[],"metadata":{"":50796," Round":"Double Jeopardy!"," Value":"$800","Answer":"Pierre Trudeau","Air Date":1990,"Category":"WORLD LEADERS","Question":"At the time this prime minister separated from his wife in '77, she denied rumors linking her with Mick Jagger","Show Number":1283},"example_id":"35184d78-6982-4ab5-a26a-febc98b6ffd1","annotations":[],"classifications":[]},{"content":"We're mostly 4,000 feet above sea level & Idi Amin doesn't run us anymore.  Isn't that enough? Uganda","seen_by":[],"comments":[],"metadata":{"":10111," Round":"Jeopardy!"," Value":"$200","Answer":"Uganda","Air Date":2010,"Category":"IDEAS FOR TOURISM CAMPAIGNS","Question":"We're mostly 4,000 feet above sea level & Idi Amin doesn't run us anymore.  Isn't that enough?","Show Number":5825},"example_id":"a703e31b-bff2-4a01-90a3-e2f77ef635d3","annotations":[],"classifications":[]},{"content":"This name is the 4-letter stock symbol of Golden Bear Golf Inc., which went public in 1996 JACK (for Jack Nicklaus)","seen_by":[{"annotator":"5ung03park@gmail.com","annotator_id":1}],"comments":[],"metadata":{"":94571," Round":"Final Jeopardy!"," Value":null,"Answer":"JACK (for Jack Nicklaus)","Air Date":1997,"Category":"STOCK SYMBOLS","Question":"This name is the 4-letter stock symbol of Golden Bear Golf Inc., which went public in 1996","Show Number":2955},"example_id":"6ac02e18-4a2a-4240-bf7d-ea8f551f3e6d","annotations":[{"end":114,"tag":"PEOPLE","start":101,"value":"Jack Nicklaus","tag_id":"f7c4b9da-4b88-4868-b5dd-dfd480135793","correct":null,"reviewed":false,"example_id":"6ac02e18-4a2a-4240-bf7d-ea8f551f3e6d","annotated_by":[{"annotator":"5ung03park@gmail.com","timestamp":"2023-12-08T02:42:26.839+00:00","annotator_id":1}],"definition_id":"fcb9cf65-33bb-4dfd-8024-11d7fbfcc2a2","tagged_token_id":"e2eb1f5a-44de-4706-85da-8fa4ad30e653"},{"end":90,"tag":"DATE","start":86,"value":"1996","tag_id":"129ac4c8-a7cb-4f8a-bcc6-a9d014adcffd","correct":null,"reviewed":false,"example_id":"6ac02e18-4a2a-4240-bf7d-ea8f551f3e6d","annotated_by":[{"annotator":"5ung03park@gmail.com","timestamp":"2023-12-08T02:42:07.546+00:00","annotator_id":1}],"definition_id":"fcb9cf65-33bb-4dfd-8024-11d7fbfcc2a2","tagged_token_id":"84a0a9a8-a1e1-4bf5-85e2-b8c8e13f54c8"},{"end":62,"tag":"ORG","start":42,"value":"Golden Bear Golf Inc","tag_id":"39ae4a0a-5402-426f-8199-adacd261960b","correct":null,"reviewed":false,"example_id":"6ac02e18-4a2a-4240-bf7d-ea8f551f3e6d","annotated_by":[{"annotator":"5ung03park@gmail.com","timestamp":"2023-12-08T02:42:18.86+00:00","annotator_id":1}],"definition_id":"fcb9cf65-33bb-4dfd-8024-11d7fbfcc2a2","tagged_token_id":"4427cee0-44eb-4847-a063-5d0a6963cdba"}],"classifications":[]},{"content":"Mata Hari pretended to be Asian, but she was actually born in this European country The Netherlands/Holland","seen_by":[],"comments":[],"metadata":{"":165252," Round":"Double Jeopardy!"," Value":"$800","Answer":"The Netherlands/Holland","Air Date":1994,"Category":"WOMEN IN HISTORY","Question":"Mata Hari pretended to be Asian, but she was actually born in this European country","Show Number":2353},"example_id":"ad77deee-b497-4a63-8322-4a426a8ac7f2","annotations":[],"classifications":[]},{"content":"An impressive display of power or skill; you might say Lance Armstrong put one on in 1999 & in 2000 a tour de force","seen_by":[],"comments":[],"metadata":{"":147258," Round":"Double Jeopardy!"," Value":"$800","Answer":"a tour de force","Air Date":2000,"Category":"PHRENCH PHRASES","Question":"An impressive display of power or skill; you might say Lance Armstrong put one on in 1999 & in 2000","Show Number":3711},"example_id":"8f5d2199-bea9-442b-9207-6be511b0bd1f","annotations":[],"classifications":[]},{"content":"It held referendums in 1980 & 1995 to decide whether to secede from Canada Quebec","seen_by":[],"comments":[],"metadata":{"":81019," Round":"Double Jeopardy!"," Value":"$800","Answer":"Quebec","Air Date":2005,"Category":"IF AT FIRST YOU DON'T SECEDE...","Question":"It held referendums in 1980 & 1995 to decide whether to secede from Canada","Show Number":4682},"example_id":"e5f88382-d27b-4afd-967f-053641d3a5f5","annotations":[],"classifications":[]},{"content":"In 1892 this French artist portrayed dancer La Goulue entering the Moulin Rouge Toulouse-Lautrec","seen_by":[],"comments":[],"metadata":{"":66421," Round":"Double Jeopardy!"," Value":"$600","Answer":"Toulouse-Lautrec","Air Date":1994,"Category":"ART","Question":"In 1892 this French artist portrayed dancer La Goulue entering the Moulin Rouge","Show Number":2351},"example_id":"adc24291-3ce0-4582-b84f-846861c2be39","annotations":[],"classifications":[]},{"content":"In 1985 this playwright's \"Requiem For A Heavyweight\" came to Broadway starring John Lithgow Rod Serling","seen_by":[],"comments":[],"metadata":{"":176876," Round":"Double Jeopardy!"," Value":"$400","Answer":"Rod Serling","Air Date":1997,"Category":"PLAYS & PLAYWRIGHTS","Question":"In 1985 this playwright's \"Requiem For A Heavyweight\" came to Broadway starring John Lithgow","Show Number":2970},"example_id":"18fe6ac2-4476-40ee-8493-565c97076b5b","annotations":[],"classifications":[]},{"content":"In the 1880s Ontario-brewed Club whiskey got this new national name Canadian Club","seen_by":[],"comments":[],"metadata":{"":9102," Round":"Jeopardy!"," Value":"$800","Answer":"Canadian Club","Air Date":2002,"Category":"HAVE A WHISKEY","Question":"In the 1880s Ontario-brewed Club whiskey got this new national name","Show Number":4160},"example_id":"2990bb02-7714-44d3-980b-7c66aeb8e2a5","annotations":[],"classifications":[]},{"content":"Daniel told this king, \"They shall drive thee from men, and thy dwelling shall be with the beasts of the field\" Nebuchadnezzar","seen_by":[],"comments":[],"metadata":{"":52981," Round":"Jeopardy!"," Value":"$500","Answer":"Nebuchadnezzar","Air Date":2000,"Category":"OLD TESTAMENT PEOPLE","Question":"Daniel told this king, \"They shall drive thee from men, and thy dwelling shall be with the beasts of the field\"","Show Number":3550},"example_id":"5a57272e-e850-43c7-bf60-b2f9d6d540e2","annotations":[],"classifications":[]},{"content":"From the 1500s to the 1800s, these pirates used the area as a base for raids on European shipping Barbary pirates","seen_by":[],"comments":[],"metadata":{"":147805," Round":"Double Jeopardy!"," Value":"$1000","Answer":"Barbary pirates","Air Date":2000,"Category":"THE HISTORY OF LIBYA","Question":"From the 1500s to the 1800s, these pirates used the area as a base for raids on European shipping","Show Number":3693},"example_id":"a6a6c768-47e2-4ee6-b7da-7a4b1fa2f7a6","annotations":[],"classifications":[]},{"content":"3-word phrase for \"a person not acceptable\" to the host country as the head of a diplomatic mission persona non grata","seen_by":[],"comments":[],"metadata":{"":13477," Round":"Double Jeopardy!"," Value":"$1600","Answer":"persona non grata","Air Date":2005,"Category":"LATIN LEGAL TERMS","Question":"3-word phrase for \"a person not acceptable\" to the host country as the head of a diplomatic mission","Show Number":4726},"example_id":"9c9d5298-cc52-46fa-95bb-482f2ccbe963","annotations":[],"classifications":[]}],"schema":{"id":"191fdc77-0220-457a-8662-d22d0c186ef4","archived":false,"slug":"annotation","name":"Annotation","tags":[{"id":"129ac4c8-a7cb-4f8a-bcc6-a9d014adcffd","name":"DATE","description":"","schema_id":"191fdc77-0220-457a-8662-d22d0c186ef4"},{"id":"82c96137-9d27-47c9-ab55-301964005870","name":"GPE","description":"","schema_id":"191fdc77-0220-457a-8662-d22d0c186ef4"},{"id":"ece814a0-aef4-41ba-bc69-a08aeadbd2ad","name":"kkkk","description":"","schema_id":"191fdc77-0220-457a-8662-d22d0c186ef4"},{"id":"6f51f024-c9b2-43e3-9795-23628c154a9e","name":"LOCATION","description":"","schema_id":"191fdc77-0220-457a-8662-d22d0c186ef4"},{"id":"39ae4a0a-5402-426f-8199-adacd261960b","name":"ORG","description":"","schema_id":"191fdc77-0220-457a-8662-d22d0c186ef4"},{"id":"f7c4b9da-4b88-4868-b5dd-dfd480135793","name":"PEOPLE","description":"","schema_id":"191fdc77-0220-457a-8662-d22d0c186ef4"}],"classification_types":[],"models":[{"id":"790fb967-83c7-48b6-8e8f-69d2bdc921ec","url":"/api/v2/models/790fb967-83c7-48b6-8e8f-69d2bdc921ec/","slug":"annotation-ad-hoc-dict","name":"Annotation ad hoc dict","metadata":{},"schema_id":"191fdc77-0220-457a-8662-d22d0c186ef4"}],"editable":false,"is_multiclass":false},"dataset":{"id":"25b254ae-e74f-42e7-853e-d2936cc089cf","slug":"jeopardy-2","url":"/api/v1/projects/default/datasets/jeopardy-2/","name":"jeopardy","id_field":null,"content_field":"Document","aggregation_field":null,"order_field":null,"upload_status":"started","archived":false,"editable":false},"relations":[],"name":"manual annotation","annotators_per_example":"1"}